Metadata-Version: 2.1
Name: PyMUMPS
Version: 0.3.3
Summary: Python bindings for MUMPS, a parallel sparse direct solver
Home-page: http://github.com/pymumps/pymumps
Author: Bradley M. Froehle
Author-email: brad.froehle@gmail.com
Maintainer: Stephan Rave
Maintainer-email: stephan.rave@uni-muenster.de
License: BSD
Classifier: Development Status :: 3 - Alpha
Classifier: Intended Audience :: Science/Research
Classifier: License :: OSI Approved :: BSD License
Classifier: Programming Language :: Python :: 2
Classifier: Programming Language :: Python :: 3
Classifier: Topic :: Scientific/Engineering :: Mathematics
License-File: COPYING
Requires-Dist: mpi4py
